{
    "affiliate": [
        {
            "id": 1,
            "nama_produk": "AL JEDDAH KUBAH MOTIF 70x110cm Sajadah Kubah Motif Aesthetic AntiSlip Jumbo Busa Tebal Empuk Premium",
            "harga": 65000,
            "rating": 4.8,
            "terjual": "4RB+",
            "gambar_url": [
                "https://cdn.jsdelivr.net/gh/sscorpfam/affiliate@main/sajadah/sj1.jpg",
                "https://cdn.jsdelivr.net/gh/sscorpfam/affiliate@main/sajadah/sj2.jpg",
                "https://cdn.jsdelivr.net/gh/sscorpfam/affiliate@main/sajadah/sj3.jpg",
                "https://cdn.jsdelivr.net/gh/sscorpfam/affiliate@main/sajadah/sj4.jpg",
                "https://cdn.jsdelivr.net/gh/sscorpfam/affiliate@main/sajadah/sj5.jpg",
                "https://cdn.jsdelivr.net/gh/sscorpfam/affiliate@main/sajadah/sj6.jpg",
                "https://cdn.jsdelivr.net/gh/sscorpfam/affiliate@main/sajadah/sj7.jpg",
                "https://cdn.jsdelivr.net/gh/sscorpfam/affiliate@main/sajadah/sj8.jpg"
            ],
            "link_affiliate": "https://s.shopee.co.id/AADJqna8HP",
            "deskripsi": "<h5>Deskripsi Produk</h5><br>\nSajadah Kubah Motif New Modern Floral Elegant Luxury Ukuran 70x110 Sejadah Viral<br><br>Made by Al Jeddah<br>Bahan: Cashmere Print + Anti Slip<br>Ukuran: 70 x 110 cm<br>Ketebalan : 3 mm<br>Tersedia variant motif Modern dan Floral<br><br>Real Pict<br>"
        },
        {
            "id": 2,
            "nama_produk": "An-Najah Sajadah Travel Gulung / Genggam Anti Slip Premium Waterproof cocok untuk Traveling Outdoor",
            "harga": 66838,
            "rating": 4.9,
            "terjual": "10RB+",
            "gambar_url": [
                "https://cdn.jsdelivr.net/gh/sscorpfam/affiliate@main/sajadah/st1.jpg",
                "https://cdn.jsdelivr.net/gh/sscorpfam/affiliate@main/sajadah/st2.jpg",
                "https://cdn.jsdelivr.net/gh/sscorpfam/affiliate@main/sajadah/st3.jpg",
                "https://cdn.jsdelivr.net/gh/sscorpfam/affiliate@main/sajadah/st4.jpg",
                "https://github.com/sscorpfam/affiliate/blob/main/sajadah/st5.jpg",
                "https://cdn.jsdelivr.net/gh/sscorpfam/affiliate@main/sajadah/st6.jpg",
                "https://cdn.jsdelivr.net/gh/sscorpfam/affiliate@main/sajadah/st7.jpg",
                "https://cdn.jsdelivr.net/gh/sscorpfam/affiliate@main/sajadah/st8.jpg"
            ],
            "link_affiliate": "https://s.shopee.co.id/9paTTCBx8T",
            "deskripsi": "<h5>Deskripsi Produk</h5><br>\nAn-Najah Sajadah Travel Gulung / Genggam Anti Slip Premium Waterproof cocok untuk Traveling Outdoor<br><br>Sajadah travel yang dapat di lipat / gulung sangat kecil sehingga sangat praktis disimpan dan dibawa kemanapun.<br>Sajadah travel ini wajib anda miliki untuk menjaga kebersihan dan kesucian tempat sujud anda agar lebih khusyuk dan nyaman saat beribadah dimanapun.<br>Sajadah travel ini bisa dijadikan pouch genggam dan terdapat gantungan hook/pengait untuk ditempelkan di tas, celana dan di saku.<br><br>Detail Ukuran :<br>Size Ketika sajadah travel di buka : 47cm X 95cm<br>Size Ketika sajadah travel di gulung : 5cm X 13cm<br>Toleransi 1-2 cm<br><br>Spesifikasi Sajadah :<br>- Sajadah Travel Real Waterproof (Anti Air)<br>- Bisa disemprotkan desifektan agar lebih steril ketika sholat<br>- Mudah dibersihkan, cukup usap pakai tisu/kain bersih cocok untuk outdoor<br>- ANTI SLIP, Lapisan bawah dilapisi bahan spot anti slip<br>- Jahitan rapi dan kuat<br>- Desain/Motif Full Printing Sublimation High Technology<br>- Motif Warna tajam, tahan lama dan tidak luntur, awet bertahun-tahun<br>- Banyak pilihan desain modern dan minimalist<br>"
        },
        {
            "id": 3,
            "nama_produk": "",
            "harga": 0,
            "rating": 5,
            "terjual": "154",
            "gambar_url": [
                "",
                "",
                "",
                "",
                "",
                ""
            ],
            "link_affiliate": "",
            "deskripsi": "<h5>Deskripsi Produk</h5><br>\n"
        },
        {
            "id": 4,
            "nama_produk": "",
            "harga": 0,
            "rating": 5,
            "terjual": "154",
            "gambar_url": [
                "",
                "",
                "",
                "",
                "",
                ""
            ],
            "link_affiliate": "",
            "deskripsi": "<h5>Deskripsi Produk</h5><br>\n"
        },
        {
            "id": 5,
            "nama_produk": "",
            "harga": 0,
            "rating": 5,
            "terjual": "154",
            "gambar_url": [
                "",
                "",
                "",
                "",
                "",
                ""
            ],
            "link_affiliate": "",
            "deskripsi": "<h5>Deskripsi Produk</h5><br>\n"
        },
        {
            "id": 6,
            "nama_produk": "",
            "harga": 0,
            "rating": 5,
            "terjual": "154",
            "gambar_url": [
                "",
                "",
                "",
                "",
                "",
                ""
            ],
            "link_affiliate": "",
            "deskripsi": "<h5>Deskripsi Produk</h5><br>\n"
        },
        {
            "id": 7,
            "nama_produk": "",
            "harga": 0,
            "rating": 5,
            "terjual": "154",
            "gambar_url": [
                "",
                "",
                "",
                "",
                "",
                ""
            ],
            "link_affiliate": "",
            "deskripsi": "<h5>Deskripsi Produk</h5><br>\n"
        },
        {
            "id": 8,
            "nama_produk": "",
            "harga": 0,
            "rating": 5,
            "terjual": "154",
            "gambar_url": [
                "",
                "",
                "",
                "",
                "",
                ""
            ],
            "link_affiliate": "",
            "deskripsi": "<h5>Deskripsi Produk</h5><br>\n"
        },
        {
            "id": 9,
            "nama_produk": "",
            "harga": 0,
            "rating": 5,
            "terjual": "154",
            "gambar_url": [
                "",
                "",
                "",
                "",
                "",
                ""
            ],
            "link_affiliate": "",
            "deskripsi": "<h5>Deskripsi Produk</h5><br>\n"
        },
        {
            "id": 10,
            "nama_produk": "",
            "harga": 0,
            "rating": 5,
            "terjual": "154",
            "gambar_url": [
                "",
                "",
                "",
                "",
                "",
                ""
            ],
            "link_affiliate": "",
            "deskripsi": "<h5>Deskripsi Produk</h5><br>\n"
        }
    ]
}